latex_generator/__init__.py
latex_generator/latex_generator.py
latex_generator_vejeja-0.1.0.dist-info/METADATA
latex_generator_vejeja-0.1.0.dist-info/WHEEL
latex_generator_vejeja-0.1.0.dist-info/RECORD
