Metadata-Version: 2.3
Name: latex-generator-vejeja
Version: 0.1.0
Summary: Функциональный генератор LaTeX для таблиц и изображений
Author: Vejeja
Author-email: kornilova.valeriia@gmail.com
Requires-Python: >=3.12
Classifier: Programming Language :: Python :: 3
Classifier: Programming Language :: Python :: 3.12
Classifier: Programming Language :: Python :: 3.13
